setup.py
dopterian/__init__.py
dopterian/auxiliary_functions_sdss.py
dopterian/cosmology.py
dopterian/dopterian.py
dopterian/dopterian_sdss.py
dopterian.egg-info/PKG-INFO
dopterian.egg-info/SOURCES.txt
dopterian.egg-info/dependency_links.txt
dopterian.egg-info/requires.txt
dopterian.egg-info/top_level.txt