Metadata-Version: 1.1
Name: dopterian
Version: 0.0.0
Summary: A code to artificially redshifting local galaxies.
Home-page: UNKNOWN
Author: Ana Paulino-Afonso
Author-email: asofiafonso@gmail.com
License: MIT
Keywords: redshifting galaxies
Platform: UNKNOWN
Classifier: Development Status :: 3 - Alpha
Classifier: Intended Audience :: Developers
Classifier: Topic :: Software Development :: Build Tools
Classifier: License :: OSI Approved :: MIT License
Classifier: Programming Language :: Python :: 2
Classifier: Programming Language :: Python :: 2.7
Classifier: Programming Language :: Python :: 3
Classifier: Programming Language :: Python :: 3.3
Classifier: Programming Language :: Python :: 3.4
Classifier: Programming Language :: Python :: 3.5
